proxybootstrap/Dockerfile.jinja2
proxybootstrap/__init__.py
proxybootstrap/nginx.default.jinja2
proxybootstrap/proxy.py
proxybootstrap-0.1.8.dist-info/LICENSE
proxybootstrap-0.1.8.dist-info/METADATA
proxybootstrap-0.1.8.dist-info/WHEEL
proxybootstrap-0.1.8.dist-info/entry_points.txt
proxybootstrap-0.1.8.dist-info/top_level.txt
proxybootstrap-0.1.8.dist-info/RECORD
