Metadata-Version: 2.1
Name: proxybootstrap
Version: 0.1.8
Summary: A simple python wrapper script for bootstrapping a reverse proxy inside a docker container.
Home-page: https://github.com/romnn/proxybootstrap
Author: romnn
Author-email: contact@romnn.com
License: MIT
Keywords: reverse,proxy,container,docker,wrapper,CORS,nginx
Platform: UNKNOWN
Classifier: Environment :: Console
Classifier: Operating System :: OS Independent
Classifier: Development Status :: 4 - Beta
Classifier: Intended Audience :: Developers
Classifier: Topic :: Software Development :: Build Tools
Classifier: License :: OSI Approved :: MIT License
Classifier: Programming Language :: Python
Classifier: Programming Language :: Python :: 3 :: Only
Classifier: Programming Language :: Python :: 3.6
Classifier: Programming Language :: Python :: 3.7
Classifier: Programming Language :: Python :: 3.8
Requires-Python: >=3.6
Requires-Dist: jinja2
Provides-Extra: dev
Requires-Dist: m2r ; extra == 'dev'
